setup.py
pycloner/__init__.py
pycloner/pycloner.py
pycloner/utils.py
pycloner.egg-info/PKG-INFO
pycloner.egg-info/SOURCES.txt
pycloner.egg-info/dependency_links.txt
pycloner.egg-info/requires.txt
pycloner.egg-info/top_level.txt