Metadata-Version: 1.1
Name: pycloner
Version: 0.1.0b3
Summary: pycloner is a package that tries to help in the process of manually crawling a website.
Home-page: http://github.com/i3visio/pycloner
Author: Felix Brezo and Yaiza Rubio
Author-email: contacto@i3visio.com
License: COPYING
Keywords: python osint harvesting crawling cloning
Platform: UNKNOWN
Classifier: Development Status :: 4 - Beta
Classifier: Topic :: Software Development :: Libraries
Classifier: License :: OSI Approved :: GNU General Public License v3 or later (GPLv3+)
Classifier: Programming Language :: Python :: 2 :: Only
Classifier: Programming Language :: Python :: 2.7
Classifier: Intended Audience :: Developers
Classifier: Intended Audience :: Information Technology
Classifier: Intended Audience :: Science/Research
Classifier: Intended Audience :: Telecommunications Industry
Classifier: Natural Language :: English
Classifier: Topic :: Communications
Classifier: Topic :: Internet :: WWW/HTTP :: Indexing/Search
Classifier: Topic :: Scientific/Engineering :: Information Analysis
Classifier: Topic :: Text Processing :: Markup :: HTML
